typeman/__init__.py
typeman/main.py
typeman/assets/common_words.txt
typeman-0.1.2.dist-info/licenses/LICENSE
typeman-0.1.2.dist-info/METADATA
typeman-0.1.2.dist-info/WHEEL
typeman-0.1.2.dist-info/entry_points.txt
typeman-0.1.2.dist-info/top_level.txt
typeman-0.1.2.dist-info/RECORD
