Metadata-Version: 2.4
Name: typeman
Version: 0.1.2
Summary: Add your description here
Project-URL: Repository, https://github.com/Sai-Suraj-27/Typeman
Project-URL: Issues, https://github.com/Sai-Suraj-27/Typeman/issues
Project-URL: Homepage, https://github.com/Sai-Suraj-27/Typeman
Requires-Python: >=3.11
License-File: LICENSE
Requires-Dist: readchar>=4.2.1
Requires-Dist: ruff>=0.12.2
Requires-Dist: typer>=0.16.0
Dynamic: license-file
